LICENSE-2.0.txt
MANIFEST.in
README.rst
arvados_version.py
setup.py
arvados_pam/__init__.py
arvados_pam/_version.py
arvados_pam/auth_event.py
arvados_pam.egg-info/PKG-INFO
arvados_pam.egg-info/SOURCES.txt
arvados_pam.egg-info/dependency_links.txt
arvados_pam.egg-info/not-zip-safe
arvados_pam.egg-info/requires.txt
arvados_pam.egg-info/top_level.txt
examples/shellinabox
lib/libpam_arvados.py
pam-configs/arvados