Metadata-Version: 1.1
Name: arvados-pam
Version: 1.4.0
Summary: Arvados PAM module
Home-page: https://arvados.org
Author: Arvados
Author-email: info@arvados.org
License: Apache 2.0
Download-URL: https://github.com/curoverse/arvados.git
Platform: UNKNOWN
